redisca
