Metadata-Version: 1.1
Name: redisca
Version: 1.0
Summary: Lightweight ORM for Redis
Home-page: http://github.com/khamin/redisca
Author: Vitaliy Khamin
Author-email: vitaliykhamin@gmail.com
License: UNKNOWN
Platform: any
Classifier: Operating System :: OS Independent
Classifier: Development Status :: 4 - Beta
Classifier: Programming Language :: Python :: 2.7
Classifier: Programming Language :: Python :: 3.2
Classifier: Programming Language :: Python :: 3.3
Classifier: Topic :: Database
